{
  "date": "2026-03-25",
  "data_gaps": [],
  "market": {
    "market_cap": 2417642258268.2,
    "prev_market_cap": 2426522821630.58,
    "volume_24h": 95659652802.62,
    "prev_volume_24h": 124726403123.08,
    "btc_dom": 58.349,
    "prev_btc_dom": 58.4511
  },
  "counts": {
    "top_assets": 10,
    "exchanges": 10,
    "stablecoin_yields": 24
  },
  "top2_trend": {
    "BTC": {
      "symbol": "BTCUSDT",
      "price": 71324.65,
      "open": 70890.94,
      "high": 72026.09,
      "low": 68923.07,
      "change_pct": 0.612,
      "range_pos_pct": 77.39492494408657,
      "trend": "区间震荡"
    },
    "ETH": {
      "symbol": "ETHUSDT",
      "price": 2171.64,
      "open": 2160.77,
      "high": 2199.02,
      "low": 2103.02,
      "change_pct": 0.503,
      "range_pos_pct": 71.47916666666654,
      "trend": "区间震荡"
    }
  },
  "top2_intraday_points": {
    "BTC": 23,
    "ETH": 23
  },
  "coingecko": {
    "status": "ok",
    "configured_tier": "demo",
    "attempted": [
      "demo"
    ],
    "used": "demo",
    "endpoint": "/coins/markets",
    "key_required": true,
    "key_present": true,
    "errors": []
  },
  "stablecoin_yields": [
    {
      "protocol": "Aave",
      "protocol_key": "aave-v3",
      "chain": "Ethereum",
      "asset": "USDT",
      "supply_apy": 1.89814,
      "borrow_apy": null,
      "rewards_apy": null,
      "total_apy": 1.89814,
      "tvl_usd": 1537012376.0,
      "total_supply_usd": null,
      "total_borrow_usd": null,
      "utilization_pct": null,
      "data_completeness": 2,
      "pool_id": "f981a304-bb6c-45b8-b0c5-fd2f515ad23a",
      "risk_note": "审计成熟/头部流动性",
      "updated_at": "2026-03-25T12:50:14.855178+00:00",
      "safety_rank": 1
    },
    {
      "protocol": "Aave",
      "protocol_key": "aave-v3",
      "chain": "Ethereum",
      "asset": "USDC",
      "supply_apy": 2.23089,
      "borrow_apy": null,
      "rewards_apy": null,
      "total_apy": 2.23089,
      "tvl_usd": 838333964.0,
      "total_supply_usd": null,
      "total_borrow_usd": null,
      "utilization_pct": null,
      "data_completeness": 2,
      "pool_id": "aa70268e-4b52-42bf-a116-608b370f9501",
      "risk_note": "审计成熟/头部流动性",
      "updated_at": "2026-03-25T12:50:14.855223+00:00",
      "safety_rank": 1
    },
    {
      "protocol": "Aave",
      "protocol_key": "aave-v3",
      "chain": "Ethereum",
      "asset": "PYUSD",
      "supply_apy": 2.03881,
      "borrow_apy": null,
      "rewards_apy": null,
      "total_apy": 2.03881,
      "tvl_usd": 134119927.0,
      "total_supply_usd": null,
      "total_borrow_usd": null,
      "utilization_pct": null,
      "data_completeness": 2,
      "pool_id": "d118f505-e75f-4152-bad3-49a2dc7482bf",
      "risk_note": "审计成熟/头部流动性",
      "updated_at": "2026-03-25T12:50:14.855337+00:00",
      "safety_rank": 1
    },
    {
      "protocol": "Aave",
      "protocol_key": "aave-v3",
      "chain": "Ethereum",
      "asset": "USDS",
      "supply_apy": 0.08047,
      "borrow_apy": null,
      "rewards_apy": null,
      "total_apy": 0.08047,
      "tvl_usd": 55505462.0,
      "total_supply_usd": null,
      "total_borrow_usd": null,
      "utilization_pct": null,
      "data_completeness": 2,
      "pool_id": "e65588a1-27ad-4e20-9232-68a6cfaccf63",
      "risk_note": "审计成熟/头部流动性",
      "updated_at": "2026-03-25T12:50:14.855489+00:00",
      "safety_rank": 1
    },
    {
      "protocol": "Aave",
      "protocol_key": "aave-v3",
      "chain": "Ethereum",
      "asset": "DAI",
      "supply_apy": 2.16057,
      "borrow_apy": null,
      "rewards_apy": null,
      "total_apy": 2.16057,
      "tvl_usd": 38425258.0,
      "total_supply_usd": null,
      "total_borrow_usd": null,
      "utilization_pct": null,
      "data_completeness": 2,
      "pool_id": "3665ee7e-6c5d-49d9-abb7-c47ab5d9d4ac",
      "risk_note": "审计成熟/头部流动性",
      "updated_at": "2026-03-25T12:50:14.855547+00:00",
      "safety_rank": 1
    },
    {
      "protocol": "Spark",
      "protocol_key": "spark-savings",
      "chain": "Ethereum",
      "asset": "USDT",
      "supply_apy": 3.44,
      "borrow_apy": null,
      "rewards_apy": null,
      "total_apy": 3.44,
      "tvl_usd": 665008806.0,
      "total_supply_usd": null,
      "total_borrow_usd": null,
      "utilization_pct": null,
      "data_completeness": 2,
      "pool_id": "a5d67f7e-5b51-4a9d-969d-caf051a7f5a4",
      "risk_note": "Aave系改造/审计覆盖",
      "updated_at": "2026-03-25T12:50:14.855234+00:00",
      "safety_rank": 2
    },
    {
      "protocol": "Spark",
      "protocol_key": "spark-savings",
      "chain": "Ethereum",
      "asset": "USDC",
      "supply_apy": 3.75,
      "borrow_apy": null,
      "rewards_apy": null,
      "total_apy": 3.75,
      "tvl_usd": 385609784.0,
      "total_supply_usd": null,
      "total_borrow_usd": null,
      "utilization_pct": null,
      "data_completeness": 2,
      "pool_id": "c5c74dd1-995c-4445-9d84-3e710bad7d52",
      "risk_note": "Aave系改造/审计覆盖",
      "updated_at": "2026-03-25T12:50:14.855263+00:00",
      "safety_rank": 2
    },
    {
      "protocol": "Spark",
      "protocol_key": "sparklend",
      "chain": "Ethereum",
      "asset": "USDT",
      "supply_apy": 1.87848,
      "borrow_apy": null,
      "rewards_apy": null,
      "total_apy": 1.87848,
      "tvl_usd": 124587842.0,
      "total_supply_usd": null,
      "total_borrow_usd": null,
      "utilization_pct": null,
      "data_completeness": 2,
      "pool_id": "8fbe28b8-140d-4e37-8804-5d2aba4daded",
      "risk_note": "Aave系改造/审计覆盖",
      "updated_at": "2026-03-25T12:50:14.855366+00:00",
      "safety_rank": 2
    },
    {
      "protocol": "Aave",
      "protocol_key": "aave-v3",
      "chain": "Arbitrum",
      "asset": "USDC",
      "supply_apy": 1.46976,
      "borrow_apy": null,
      "rewards_apy": null,
      "total_apy": 1.46976,
      "tvl_usd": 105311565.0,
      "total_supply_usd": null,
      "total_borrow_usd": null,
      "utilization_pct": null,
      "data_completeness": 2,
      "pool_id": "d9fa8e14-0447-4207-9ae8-7810199dfa1f",
      "risk_note": "审计成熟/头部流动性",
      "updated_at": "2026-03-25T12:50:14.855393+00:00",
      "safety_rank": 2
    },
    {
      "protocol": "Aave",
      "protocol_key": "aave-v3",
      "chain": "Base",
      "asset": "USDC",
      "supply_apy": 2.32627,
      "borrow_apy": null,
      "rewards_apy": null,
      "total_apy": 2.32627,
      "tvl_usd": 104127023.0,
      "total_supply_usd": null,
      "total_borrow_usd": null,
      "utilization_pct": null,
      "data_completeness": 2,
      "pool_id": "7e0661bf-8cf3-45e6-9424-31916d4c7b84",
      "risk_note": "审计成熟/头部流动性",
      "updated_at": "2026-03-25T12:50:14.855401+00:00",
      "safety_rank": 2
    },
    {
      "protocol": "Spark",
      "protocol_key": "sparklend",
      "chain": "Ethereum",
      "asset": "PYUSD",
      "supply_apy": 0.83481,
      "borrow_apy": null,
      "rewards_apy": null,
      "total_apy": 0.83481,
      "tvl_usd": 77673196.0,
      "total_supply_usd": null,
      "total_borrow_usd": null,
      "utilization_pct": null,
      "data_completeness": 2,
      "pool_id": "995b269a-8409-4c55-b97e-868f443b432e",
      "risk_note": "Aave系改造/审计覆盖",
      "updated_at": "2026-03-25T12:50:14.855434+00:00",
      "safety_rank": 2
    },
    {
      "protocol": "Spark",
      "protocol_key": "sparklend",
      "chain": "Ethereum",
      "asset": "USDS",
      "supply_apy": 2.55139,
      "borrow_apy": null,
      "rewards_apy": null,
      "total_apy": 2.55139,
      "tvl_usd": 31890169.0,
      "total_supply_usd": null,
      "total_borrow_usd": null,
      "utilization_pct": null,
      "data_completeness": 2,
      "pool_id": "0ed981dc-b49d-426d-ade5-6014728b1ef9",
      "risk_note": "Aave系改造/审计覆盖",
      "updated_at": "2026-03-25T12:50:14.855576+00:00",
      "safety_rank": 2
    },
    {
      "protocol": "Spark",
      "protocol_key": "sparklend",
      "chain": "Ethereum",
      "asset": "SUSDS",
      "supply_apy": 0.0,
      "borrow_apy": null,
      "rewards_apy": null,
      "total_apy": 0.0,
      "tvl_usd": 3431790.0,
      "total_supply_usd": null,
      "total_borrow_usd": null,
      "utilization_pct": null,
      "data_completeness": 2,
      "pool_id": "d3694b72-5bc4-44c9-8ab6-1fc7941d216a",
      "risk_note": "Aave系改造/审计覆盖",
      "updated_at": "2026-03-25T12:50:14.856282+00:00",
      "safety_rank": 2
    },
    {
      "protocol": "Spark",
      "protocol_key": "sparklend",
      "chain": "Ethereum",
      "asset": "USDC",
      "supply_apy": 4.13836,
      "borrow_apy": null,
      "rewards_apy": null,
      "total_apy": 4.13836,
      "tvl_usd": 1862773.0,
      "total_supply_usd": null,
      "total_borrow_usd": null,
      "utilization_pct": null,
      "data_completeness": 2,
      "pool_id": "65ce8276-b4d9-41ba-9f6f-21fc374cf9bc",
      "risk_note": "Aave系改造/审计覆盖",
      "updated_at": "2026-03-25T12:50:14.856628+00:00",
      "safety_rank": 2
    },
    {
      "protocol": "Aave",
      "protocol_key": "aave-v3",
      "chain": "Arbitrum",
      "asset": "DAI",
      "supply_apy": 1.71878,
      "borrow_apy": null,
      "rewards_apy": null,
      "total_apy": 1.71878,
      "tvl_usd": 1738008.0,
      "total_supply_usd": null,
      "total_borrow_usd": null,
      "utilization_pct": null,
      "data_completeness": 2,
      "pool_id": "a8e3d841-2788-4647-ad54-5a36fac451b1",
      "risk_note": "审计成熟/头部流动性",
      "updated_at": "2026-03-25T12:50:14.856664+00:00",
      "safety_rank": 2
    },
    {
      "protocol": "Spark",
      "protocol_key": "spark-savings",
      "chain": "Ethereum",
      "asset": "PYUSD",
      "supply_apy": 3.75,
      "borrow_apy": null,
      "rewards_apy": null,
      "total_apy": 3.75,
      "tvl_usd": 465845.0,
      "total_supply_usd": null,
      "total_borrow_usd": null,
      "utilization_pct": null,
      "data_completeness": 2,
      "pool_id": "4d33c615-a969-4c55-9acf-49d8d14a1063",
      "risk_note": "Aave系改造/审计覆盖",
      "updated_at": "2026-03-25T12:50:14.857432+00:00",
      "safety_rank": 2
    },
    {
      "protocol": "Compound",
      "protocol_key": "compound-v3",
      "chain": "Ethereum",
      "asset": "USDC",
      "supply_apy": 2.45078,
      "borrow_apy": null,
      "rewards_apy": 0.10405,
      "total_apy": 2.55482,
      "tvl_usd": 120748655.0,
      "total_supply_usd": null,
      "total_borrow_usd": null,
      "utilization_pct": null,
      "data_completeness": 3,
      "pool_id": "7da72d09-56ca-4ec5-a45f-59114353e487",
      "risk_note": "成熟协议/资金利用率驱动",
      "updated_at": "2026-03-25T12:50:14.855375+00:00",
      "safety_rank": 4
    },
    {
      "protocol": "Compound",
      "protocol_key": "compound-v3",
      "chain": "Ethereum",
      "asset": "USDT",
      "supply_apy": 2.51306,
      "borrow_apy": null,
      "rewards_apy": 0.10652,
      "total_apy": 2.61958,
      "tvl_usd": 60849200.0,
      "total_supply_usd": null,
      "total_borrow_usd": null,
      "utilization_pct": null,
      "data_completeness": 3,
      "pool_id": "f4d5b566-e815-4ca2-bb07-7bcd8bc797f1",
      "risk_note": "成熟协议/资金利用率驱动",
      "updated_at": "2026-03-25T12:50:14.855472+00:00",
      "safety_rank": 4
    },
    {
      "protocol": "Compound",
      "protocol_key": "compound-v3",
      "chain": "Arbitrum",
      "asset": "USDC",
      "supply_apy": 2.3826,
      "borrow_apy": null,
      "rewards_apy": 0.0,
      "total_apy": 2.3826,
      "tvl_usd": 7082202.0,
      "total_supply_usd": null,
      "total_borrow_usd": null,
      "utilization_pct": null,
      "data_completeness": 3,
      "pool_id": "d9c395b9-00d0-4426-a6b3-572a6dd68e54",
      "risk_note": "成熟协议/资金利用率驱动",
      "updated_at": "2026-03-25T12:50:14.855999+00:00",
      "safety_rank": 4
    },
    {
      "protocol": "Compound",
      "protocol_key": "compound-v3",
      "chain": "Arbitrum",
      "asset": "USDT",
      "supply_apy": 2.43511,
      "borrow_apy": null,
      "rewards_apy": 0.0,
      "total_apy": 2.43511,
      "tvl_usd": 6576693.0,
      "total_supply_usd": null,
      "total_borrow_usd": null,
      "utilization_pct": null,
      "data_completeness": 3,
      "pool_id": "85247b13-8180-44e7-b38c-4d324cc68a92",
      "risk_note": "成熟协议/资金利用率驱动",
      "updated_at": "2026-03-25T12:50:14.856025+00:00",
      "safety_rank": 4
    },
    {
      "protocol": "Compound",
      "protocol_key": "compound-v3",
      "chain": "Base",
      "asset": "USDC",
      "supply_apy": 2.92245,
      "borrow_apy": null,
      "rewards_apy": 0.0,
      "total_apy": 2.92245,
      "tvl_usd": 2014274.0,
      "total_supply_usd": null,
      "total_borrow_usd": null,
      "utilization_pct": null,
      "data_completeness": 3,
      "pool_id": "0c8567f8-ba5b-41ad-80de-00a71895eb19",
      "risk_note": "成熟协议/资金利用率驱动",
      "updated_at": "2026-03-25T12:50:14.856561+00:00",
      "safety_rank": 4
    },
    {
      "protocol": "Morpho",
      "protocol_key": "morpho-v1",
      "chain": "Ethereum",
      "asset": "SUSDS",
      "supply_apy": null,
      "borrow_apy": null,
      "rewards_apy": null,
      "total_apy": 0.0,
      "tvl_usd": 227084525.0,
      "total_supply_usd": null,
      "total_borrow_usd": null,
      "utilization_pct": null,
      "data_completeness": 0,
      "pool_id": "9469cde6-65d8-4bbb-ade6-8a89f1728403",
      "risk_note": "需关注金库与奖励口径差异",
      "updated_at": "2026-03-25T12:50:14.855302+00:00",
      "safety_rank": 4
    },
    {
      "protocol": "Morpho",
      "protocol_key": "morpho-v1",
      "chain": "Arbitrum",
      "asset": "SUSDS",
      "supply_apy": null,
      "borrow_apy": null,
      "rewards_apy": null,
      "total_apy": 0.0,
      "tvl_usd": 13280116.0,
      "total_supply_usd": null,
      "total_borrow_usd": null,
      "utilization_pct": null,
      "data_completeness": 0,
      "pool_id": "0fd780bc-de70-42bc-b2db-6afa5f9ad56c",
      "risk_note": "需关注金库与奖励口径差异",
      "updated_at": "2026-03-25T12:50:14.855774+00:00",
      "safety_rank": 5
    },
    {
      "protocol": "Morpho",
      "protocol_key": "morpho-v1",
      "chain": "Base",
      "asset": "USDC",
      "supply_apy": null,
      "borrow_apy": null,
      "rewards_apy": null,
      "total_apy": 0.0,
      "tvl_usd": 19112.0,
      "total_supply_usd": null,
      "total_borrow_usd": null,
      "utilization_pct": null,
      "data_completeness": 0,
      "pool_id": "7e930fdf-5a52-4982-9ce3-0323fede4918",
      "risk_note": "需关注金库与奖励口径差异",
      "updated_at": "2026-03-25T12:50:14.861850+00:00",
      "safety_rank": 5
    }
  ]
}